selenium_profiles_brand/__init__.py
selenium_profiles_brand/webdriver.py
selenium_profiles_brand/files/__init__.py
selenium_profiles_brand/files/proxy_extension/background.js
selenium_profiles_brand/files/proxy_extension/manifest.json
selenium_profiles_brand/files/tmp/__init__.py
selenium_profiles_brand/files/tmp/proxy_extension/manifest.json
selenium_profiles_brand/js/__init__.py
selenium_profiles_brand/js/export_profile.js
selenium_profiles_brand/js/fetch.js
selenium_profiles_brand/js/undetected/__init.py
selenium_profiles_brand/js/undetected/get_cdc_props.js
selenium_profiles_brand/js/undetected/navigator_webdriver.js
selenium_profiles_brand/js/undetected/remove_cdc_props.js
selenium_profiles_brand/profiles/__init__.py
selenium_profiles_brand/profiles/default.json
selenium_profiles_brand/profiles/example.json
selenium_profiles_brand/profiles/profiles.py
selenium_profiles_brand/profiles/scratch.json
selenium_profiles_brand/scripts/__init__.py
selenium_profiles_brand/scripts/driver_utils.py
selenium_profiles_brand/scripts/profiles.py
selenium_profiles_brand/scripts/proxy.py
selenium_profiles_brand/scripts/undetected.py
selenium_profiles_brand/utils/__init__.py
selenium_profiles_brand/utils/colab_utils.py
selenium_profiles_brand/utils/utils.py
selenium_profiles_brand-2.2.7.3.1.dist-info/LICENSE.md
selenium_profiles_brand-2.2.7.3.1.dist-info/METADATA
selenium_profiles_brand-2.2.7.3.1.dist-info/WHEEL
selenium_profiles_brand-2.2.7.3.1.dist-info/top_level.txt
selenium_profiles_brand-2.2.7.3.1.dist-info/RECORD
